LICENSE
iterutils/__init__.py
iterutils/py.typed
python_iterutils-0.2.10.1.dist-info/LICENSE
python_iterutils-0.2.10.1.dist-info/METADATA
python_iterutils-0.2.10.1.dist-info/WHEEL
python_iterutils-0.2.10.1.dist-info/RECORD
