Metadata-Version: 2.1
Name: python-iterutils
Version: 0.2.10.1
Summary: Python another itertools.
Home-page: https://github.com/ChenyangGao/python-modules/tree/main/python-iterutils
License: MIT
Keywords: iterable,iterutils
Author: ChenyangGao
Author-email: wosiwujm@gmail.com
Requires-Python: >=3.12,<4.0
Classifier: Development Status :: 5 - Production/Stable
Classifier: Intended Audience :: Developers
Classifier: License :: OSI Approved :: MIT License
Classifier: Operating System :: OS Independent
Classifier: Programming Language :: Python
Classifier: Programming Language :: Python :: 3
Classifier: Programming Language :: Python :: 3.12
Classifier: Programming Language :: Python :: 3.13
Classifier: Programming Language :: Python :: 3 :: Only
Classifier: Topic :: Software Development
Classifier: Topic :: Software Development :: Libraries
Classifier: Topic :: Software Development :: Libraries :: Python Modules
Requires-Dist: python-asynctools (>=0.1.3.4)
Requires-Dist: python-texttools (>=0.0.3)
Requires-Dist: python-undefined (>=0.0.3)
Project-URL: Repository, https://github.com/ChenyangGao/python-modules/tree/main/python-iterutils
